COPYING.txt
MANIFEST.in
README.md
setup.cfg
setup.py
sdfpy/__init__.py
sdfpy/sdf.py
sdfpy.egg-info/PKG-INFO
sdfpy.egg-info/SOURCES.txt
sdfpy.egg-info/dependency_links.txt
sdfpy.egg-info/requires.txt
sdfpy.egg-info/top_level.txt