Metadata-Version: 1.1
Name: sdfpy
Version: 0.1.1
Summary: Self-Describing File Reader
Home-page: http://bitbucket.org/darkskysims/sdfpy
Author: Samuel Skillman <samskillman@gmail.com>, Matthew Turk <matthewturk@gmail.com>, Michael S. Warren <mswarren@gmail.com>
Author-email: UNKNOWN
License: BSD
Keywords: data
Platform: UNKNOWN
Classifier: Programming Language :: Python
Classifier: Topic :: Software Development :: Libraries :: Python Modules
